flake8_in_file_ignores/__init__.py
flake8_in_file_ignores/flake8_plugin.py
flake8_in_file_ignores/tests/__init__.py
flake8_in_file_ignores/tests/unit/__init__.py
flake8_in_file_ignores/tests/unit/non_utf8_module.py
flake8_in_file_ignores/tests/unit/test_flake8_plugin.py
flake8_in_file_ignores/tests/unit/utils.py
flake8_in_file_ignores-0.3.0.dist-info/LICENSE
flake8_in_file_ignores-0.3.0.dist-info/METADATA
flake8_in_file_ignores-0.3.0.dist-info/WHEEL
flake8_in_file_ignores-0.3.0.dist-info/entry_points.txt
flake8_in_file_ignores-0.3.0.dist-info/top_level.txt
flake8_in_file_ignores-0.3.0.dist-info/RECORD
