Metadata-Version: 2.1
Name: flake8-in-file-ignores
Version: 0.3.0
Summary: file-level per-file-ignores for flake8
Home-page: https://github.com/bagerard/flake8-in-file-ignores
Maintainer: Bastien Gerard
Maintainer-email: bast.gerard@gmail.com
License: MIT License
Keywords: flake8 per-file-ignores
Classifier: Development Status :: 3 - Alpha
Classifier: Environment :: Console
Classifier: Intended Audience :: Developers
Classifier: License :: OSI Approved :: MIT License
Classifier: Operating System :: OS Independent
Classifier: Programming Language :: Python
Classifier: Programming Language :: Python :: 3
Classifier: Topic :: Software Development :: Libraries :: Python Modules
Classifier: Topic :: Software Development :: Quality Assurance
License-File: LICENSE
Requires-Dist: flake8
